cmd_exec/__init__.py
cmd_exec/action/CmdAction.py
cmd_exec/action/CmdActionResponse.py
cmd_exec/action/__init__.py
cmd_exec/app/CmdExecApp.py
cmd_exec/app/CmdExecAppRunner.py
cmd_exec/app/CoreCmdExecApp.py
cmd_exec/app/__init__.py
cmd_exec/builder/AppContextBuilder.py
cmd_exec/builder/__init__.py
cmd_exec/classes/FieldType.py
cmd_exec/classes/File.py
cmd_exec/classes/HtmlElement.py
cmd_exec/classes/MarkupBuilder.py
cmd_exec/classes/Option.py
cmd_exec/classes/TextColor.py
cmd_exec/classes/__init__.py
cmd_exec/command/CmdExecutor.py
cmd_exec/command/CmdRequest.py
cmd_exec/command/CmdResponse.py
cmd_exec/command/__init__.py
cmd_exec/config/AppConfigs.py
cmd_exec/config/ConfigKey.py
cmd_exec/config/ConfigManager.py
cmd_exec/config/ConfigValue.py
cmd_exec/config/__init__.py
cmd_exec/context/AppContext.py
cmd_exec/context/AppContextManager.py
cmd_exec/context/__init__.py
cmd_exec/database/Column.py
cmd_exec/database/DomainObject.py
cmd_exec/database/__init__.py
cmd_exec/date/Date.py
cmd_exec/date/__init__.py
cmd_exec/error/CmdExecError.py
cmd_exec/error/ErrorMessage.py
cmd_exec/error/__init__.py
cmd_exec/field/DateField.py
cmd_exec/field/Field.py
cmd_exec/field/OptionProvider.py
cmd_exec/field/SelectionField.py
cmd_exec/field/TextField.py
cmd_exec/field/__init__.py
cmd_exec/log/LogMessage.py
cmd_exec/log/LogSettings.py
cmd_exec/log/__init__.py
cmd_exec/menu/Command.py
cmd_exec/menu/__init__.py
cmd_exec/module/AppModule.py
cmd_exec/module/ModuleDependency.py
cmd_exec/module/ServiceProperties.py
cmd_exec/module/__init__.py
cmd_exec/service/AppService.py
cmd_exec/service/ArgumentService.py
cmd_exec/service/CommandService.py
cmd_exec/service/ConfigurationService.py
cmd_exec/service/CoreTerminalService.py
cmd_exec/service/DatabaseService.py
cmd_exec/service/FieldService.py
cmd_exec/service/LogService.py
cmd_exec/service/ServiceBuilder.py
cmd_exec/service/ServiceType.py
cmd_exec/service/TerminalService.py
cmd_exec/service/__init__.py
cmd_exec/util/AppUtil.py
cmd_exec-0.0.4.dist-info/LICENSE
cmd_exec-0.0.4.dist-info/METADATA
cmd_exec-0.0.4.dist-info/WHEEL
cmd_exec-0.0.4.dist-info/top_level.txt
cmd_exec-0.0.4.dist-info/RECORD
