Metadata-Version: 2.1
Name: cmd-exec
Version: 0.0.4
Summary: This module allows to execute python scripts.
Home-page: https://github.com/ahuyuktepe/cmd-exec
Author: Alper Huyuktepe
Author-email: alphuy@gmail.com
Project-URL: Bug Tracker, https://github.com/ahuyuktepe/cmd-exec/issues
Classifier: Programming Language :: Python :: 3
Classifier: License :: OSI Approved :: MIT License
Classifier: Operating System :: OS Independent
Requires-Python: >=3.6
License-File: LICENSE
